<Person>
<name>Francesco Clemente</name>
<variantName />
<thumbnail>https://en.wikipedia.org/wiki/Special:FilePath/&apos;Water_and_wine&apos;,_gouache_on_paper_by_Francesco_Clemente_1981.jpg?width=270</thumbnail>
<birthEN>1952</birthEN>
<birthDE>1952</birthDE>
<deathEN />
<deathDE />
<birthPlace />
<deathPlace />
<professionOrOccupation>
<XML_Serializer_Tag>Künstler</XML_Serializer_Tag>
<XML_Serializer_Tag>Maler</XML_Serializer_Tag>
<XML_Serializer_Tag>Zeichner</XML_Serializer_Tag>
</professionOrOccupation>
<artworks />
<dbpResource>http://dbpedia.org/resource/Francesco_Clemente</dbpResource>
<abstract>Francesco Clemente (* 23. März 1952 in Neapel) ist ein zeitgenössischer italienisch-US-amerikanischer Künstler. Er ist neben Sandro Chia, Enzo Cucchi und Mimmo Paladino einer der Hauptvertreter der postmodernen italienischen Transavantgarde (italienisch Transavantguardia).</abstract>
<wikilink>http://en.wikipedia.org/wiki/Francesco_Clemente?oldid=606347412</wikilink>
</Person>